.frozen_requirements.txt
CHANGES.txt
LICENSE.txt
MANIFEST.in
README.rst
setup.py
docs/basemodel.rst
docs/index.rst
docs/sqlbases.rst
docs/usingframeworks.rst
docs/_build/doctest/output.txt
docs/_build/html/_sources/README.txt
docs/_build/html/_sources/basemodel.txt
docs/_build/html/_sources/index.txt
docs/_build/html/_sources/sqlabaseclasses.txt
docs/_build/html/_sources/sqlbases.txt
docs/_build/html/_sources/usingframeworks.txt
docs/_build/linkcheck/output.txt
graph_alchemy.egg-info/PKG-INFO
graph_alchemy.egg-info/SOURCES.txt
graph_alchemy.egg-info/dependency_links.txt
graph_alchemy.egg-info/requires.txt
graph_alchemy.egg-info/top_level.txt
graphalchemy/__init__.py
graphalchemy/basemodels.py
graphalchemy/sqlmodels.py
tests/quick_testdatabase.db