Metadata-Version: 1.1
Name: graph-alchemy
Version: 0.1.0
Summary: Basic Node/Edge model for SQLAlchemy
Home-page: jeffreytratner.com
Author: Jeffrey Tratner
Author-email: jeffrey.tratner@gmail.com
License: MIT License
Download-URL: Where to download it.
Platform: UNKNOWN
Classifier: Topic :: Database :: Front-Ends
Classifier: Operating System :: OS Independent
Classifier: Programming Language :: Python
Classifier: Development Status :: 2 - Pre-Alpha
Classifier: Intended Audience :: Developers
Classifier: Intended Audience :: Science/Research
Classifier: License :: OSI Approved :: MIT License
Classifier: Topic :: Scientific/Engineering :: Information Analysis
